langchain_kipris_tools/__init__.py
langchain_kipris_tools/kipris_api/__init__.py
langchain_kipris_tools/kipris_api/abs_class.py
langchain_kipris_tools/kipris_api/applicant_search_api.py
langchain_kipris_tools/kipris_api/patent_keyword_search_api.py
langchain_kipris_tools/kipris_api/patent_search_api.py
langchain_kipris_tools/kipris_api/utils.py
langchain_kipris_tools/kipris_tools/__init__.py
langchain_kipris_tools/kipris_tools/applicant_search_tool.py
langchain_kipris_tools/kipris_tools/patent_keyword_search_tool.py
langchain_kipris_tools/kipris_tools/patent_search_tool.py
langchain_kipris_tools-0.0.2.dist-info/LICENSE
langchain_kipris_tools-0.0.2.dist-info/METADATA
langchain_kipris_tools-0.0.2.dist-info/WHEEL
langchain_kipris_tools-0.0.2.dist-info/top_level.txt
langchain_kipris_tools-0.0.2.dist-info/RECORD
